chaff_tools/__init__.py
chaff_tools/batch.py
chaff_tools/contaminate.py
chaff_tools/extract.py
chaff_tools/make_dockopt_ready.py
chaff_tools/split_db2.py
chaff_tools/tools.py
chaff_tools/tools_old.py
chaff_tools/yaml_wrangler.py
tldr_tools/__init__.py
tldr_tools/tldr_download.py
tldr_tools/tldr_endpoint.py
tldr_tools/tldr_status.py
tldr_tools/tldr_submit.py
tldr_tools-0.2.4.4.dist-info/LICENSE
tldr_tools-0.2.4.4.dist-info/METADATA
tldr_tools-0.2.4.4.dist-info/WHEEL
tldr_tools-0.2.4.4.dist-info/entry_points.txt
tldr_tools-0.2.4.4.dist-info/top_level.txt
tldr_tools-0.2.4.4.dist-info/RECORD
