Metadata-Version: 2.1
Name: tldr-tools
Version: 0.2.4.4
Summary: Use TLDR for dockopt, decoy generation, and job management.
Home-page: https://github.com/maomlab/tldr_docking
Author: Hai Pham
Author-email: haipham8315@gmail.com
Classifier: Programming Language :: Python :: 3
Classifier: License :: OSI Approved :: MIT License
Classifier: Operating System :: OS Independent
Requires-Python: >=3.10
License-File: LICENSE
Requires-Dist: requests
Requires-Dist: python-dotenv
Requires-Dist: beautifulsoup4
Requires-Dist: numpy
Requires-Dist: pyyaml
Requires-Dist: pandas
